fxlang/__init__.py
fxlang/__main__.py
fxlang/core/__init__.py
fxlang/core/ast.py
fxlang/core/environment.py
fxlang/core/execution.py
fxlang/core/parser.py
fxlang/core/values.py
fxlang-0.1.1.dist-info/WHEEL
fxlang-0.1.1.dist-info/METADATA
fxlang-0.1.1.dist-info/RECORD
