Metadata-Version: 2.1
Name: fxlang
Version: 0.1.1
Summary: 
Author: Bernardo Lourenço
Author-email: bernardo.martins.lourenco@everis.com
Requires-Python: >=3.7,<4.0
Classifier: Programming Language :: Python :: 3
Classifier: Programming Language :: Python :: 3.7
Classifier: Programming Language :: Python :: 3.8
Classifier: Programming Language :: Python :: 3.9
Requires-Dist: lark (>=0.11.3,<0.12.0)
Requires-Dist: printree (>=0.2.0,<0.3.0)
Requires-Dist: typing-extensions (>=4.0.0,<5.0.0)
